[{"id":1,"status":"[ ]","task":"Bikin aplikasi","created":"2018-06-08T01:44:47.597Z","tag":["susah","cool"]},{"id":2,"status":"[x]","task":"Bangun Pagi","created":"2018-06-08T01:46:02.507Z"},{"id":3,"status":"[x]","task":"Mandi","created":"2018-06-08T03:17:14.168Z"},{"id":4,"status":"[ ]","task":"Bangun","created":"2018-06-08T05:55:23.647Z"},{"id":5,"status":"[ ]","task":"Bangun","created":"2018-06-08T05:57:44.933Z"},{"id":6,"status":"[ ]","task":"Bangun","created":"2018-06-08T05:59:20.165Z"},{"id":7,"status":"[ ]","task":"Bangun","created":"2018-06-08T05:59:34.406Z"},{"id":8,"status":"[ ]","task":"Bangun","created":"2018-06-08T06:01:06.008Z"},{"id":9,"status":"[ ]","task":"Bangun","created":"2018-06-08T06:02:19.747Z"}]